app/__init__.py
app/cli.py
app/config.py
app/main.py
app/server.py
app/version.py
app/api/__init__.py
app/api/endpoints.py
app/core/__init__.py
app/core/audio_processor.py
app/core/base_processor.py
app/core/image_processor.py
app/core/model_registry.py
app/core/queue.py
app/core/video_processor.py
app/handler/__init__.py
app/handler/mflux.py
app/handler/mlx_embeddings.py
app/handler/mlx_lm.py
app/handler/mlx_vlm.py
app/handler/mlx_whisper.py
app/handler/parser/__init__.py
app/handler/parser/base.py
app/handler/parser/factory.py
app/handler/parser/glm4_moe.py
app/handler/parser/harmony.py
app/handler/parser/hermes.py
app/handler/parser/llama4_pythonic.py
app/handler/parser/minimax.py
app/handler/parser/ministral3.py
app/handler/parser/nemotron3_nano.py
app/handler/parser/qwen3.py
app/handler/parser/qwen3_moe.py
app/handler/parser/qwen3_next.py
app/handler/parser/qwen3_vl.py
app/message_converters/__init__.py
app/message_converters/abstract_converter.py
app/message_converters/glm4_moe.py
app/message_converters/minimax_m2.py
app/message_converters/nemontron3_nano.py
app/message_converters/qwen3_coder.py
app/middleware/__init__.py
app/middleware/request_tracking.py
app/models/__init__.py
app/models/mflux.py
app/models/mlx_embeddings.py
app/models/mlx_lm.py
app/models/mlx_vlm.py
app/models/mlx_whisper.py
app/parsers/__init__.py
app/parsers/abstract_parser.py
app/parsers/function_parameter.py
app/parsers/functiongemma.py
app/parsers/glm4_moe.py
app/parsers/harmony.py
app/parsers/hermes.py
app/parsers/iquest_coder_v1.py
app/parsers/minimax_m2.py
app/parsers/nemotron3_nano.py
app/parsers/qwen3.py
app/parsers/qwen3_coder.py
app/parsers/qwen3_moe.py
app/parsers/qwen3_vl.py
app/parsers/solar_open.py
app/schemas/__init__.py
app/schemas/model.py
app/schemas/openai.py
app/utils/__init__.py
app/utils/debug_logging.py
app/utils/dill.py
app/utils/errors.py
app/utils/outlines_transformer_tokenizer.py
app/utils/prompt_cache.py
mlx_openai_server-1.5.0.dist-info/licenses/LICENSE
mlx_openai_server-1.5.0.dist-info/METADATA
mlx_openai_server-1.5.0.dist-info/WHEEL
mlx_openai_server-1.5.0.dist-info/entry_points.txt
mlx_openai_server-1.5.0.dist-info/top_level.txt
mlx_openai_server-1.5.0.dist-info/RECORD
