Metadata-Version: 2.4
Name: mlx-openai-server
Version: 1.5.0
Summary: A high-performance API server that provides OpenAI-compatible endpoints for MLX models.
Author-email: Gia-Huy Vuong <cubist38@gmail.com>
License: MIT
Project-URL: Homepage, https://github.com/cubist38/mlx-openai-server
Keywords: mlx,fastapi,openai,server,api,multimodal,local models
Classifier: Programming Language :: Python :: 3
Classifier: License :: OSI Approved :: MIT License
Classifier: Operating System :: OS Independent
Requires-Python: <3.13,>=3.11
License-File: LICENSE
Requires-Dist: aiofiles<26,>=25
Requires-Dist: av<17,>=16.0.1
Requires-Dist: click<8.4,>=8.2.1
Requires-Dist: fastapi<0.130,>=0.115.14
Requires-Dist: httpx<1,>=0.28
Requires-Dist: json_repair<0.60,>=0.52.1
Requires-Dist: librosa<0.12,>=0.11.0
Requires-Dist: mflux<0.14,>=0.13.2
Requires-Dist: loguru<0.8,>=0.7.3
Requires-Dist: mlx-embeddings<0.1,>=0.0.4
Requires-Dist: mlx-lm<0.31,>=0.30.2
Requires-Dist: mlx-vlm<0.4,>=0.3.9
Requires-Dist: mlx-whisper<0.5,>=0.4.3
Requires-Dist: mlx>=0.30
Requires-Dist: numpy<2.4,>=2.2.0
Requires-Dist: openai-harmony<0.1,>=0.0.8
Requires-Dist: outlines<1.2,>=1.1.1
Requires-Dist: pillow<11.0,>=10.4.0
Requires-Dist: pydantic<3,>=2
Requires-Dist: python-multipart<0.0.25,>=0.0.20
Requires-Dist: rich<15,>=14
Requires-Dist: torchvision<0.30,>=0.23.0
Requires-Dist: uvicorn<0.40,>=0.35.0
Dynamic: license-file
